topsis_analysis.py
topsis_analysis-0.0.3.dist-info/LICENSE.txt
topsis_analysis-0.0.3.dist-info/METADATA
topsis_analysis-0.0.3.dist-info/WHEEL
topsis_analysis-0.0.3.dist-info/top_level.txt
topsis_analysis-0.0.3.dist-info/RECORD
